Workbook

Sheet Summary
A1: fable-mode-pro v6.1 vs. old rules: blind checker test
A2: Old = fable-mode v6 step 3/4 rules. New = v6.1 with error-first judgment check (adapted from Ali Assem's wise-men-flash, MIT).
A4: Test | B4: Rules | C4: Checkers | D4: Caught | E4: Planted (total) | F4: Catch rate | G4: Dissent flagged | H4: Decoys wrongly flagged | I4: Nitpick false flags | J4: Judgment labeled | K4: Avg tokens
A5: Test 1: Coravin | B5: Old (A) | C5: =COUNTIFS(Checkers!$A$2:$A$13,$A5,Checkers!$B$2:$B$13,$B5) -> 3 | D5: =SUMIFS(Checkers!$F$2:$F$13,Checkers!$A$2:$A$13,$A5,Checkers!$B$2:$B$13,$B5) -> 24 | E5: =SUMIFS(Checkers!$E$2:$E$13,Checkers!$A$2:$A$13,$A5,Checkers!$B$2:$B$13,$B5) -> 24 | F5: =D5/E5 -> 1 | G5: =SUMIFS(Checkers!$I$2:$I$13,Checkers!$A$2:$A$13,$A5,Checkers!$B$2:$B$13,$B5)&" of "&C5 -> 3 of 3 | H5: =SUMIFS(Checkers!$J$2:$J$13,Checkers!$A$2:$A$13,$A5,Checkers!$B$2:$B$13,$B5) -> 0 | I5: =SUMIFS(Checkers!$K$2:$K$13,Checkers!$A$2:$A$13,$A5,Checkers!$B$2:$B$13,$B5) -> 0 | J5: =SUMIFS(Checkers!$L$2:$L$13,Checkers!$A$2:$A$13,$A5,Checkers!$B$2:$B$13,$B5)&" of "&C5 -> 0 of 3 | K5: =AVERAGEIFS(Checkers!$M$2:$M$13,Checkers!$A$2:$A$13,$A5,Checkers!$B$2:$B$13,$B5) -> 86350
A6: Test 1: Coravin | B6: New (B) | C6: =COUNTIFS(Checkers!$A$2:$A$13,$A6,Checkers!$B$2:$B$13,$B6) -> 3 | D6: =SUMIFS(Checkers!$F$2:$F$13,Checkers!$A$2:$A$13,$A6,Checkers!$B$2:$B$13,$B6) -> 24 | E6: =SUMIFS(Checkers!$E$2:$E$13,Checkers!$A$2:$A$13,$A6,Checkers!$B$2:$B$13,$B6) -> 24 | F6: =D6/E6 -> 1 | G6: =SUMIFS(Checkers!$I$2:$I$13,Checkers!$A$2:$A$13,$A6,Checkers!$B$2:$B$13,$B6)&" of "&C6 -> 3 of 3 | H6: =SUMIFS(Checkers!$J$2:$J$13,Checkers!$A$2:$A$13,$A6,Checkers!$B$2:$B$13,$B6) -> 0 | I6: =SUMIFS(Checkers!$K$2:$K$13,Checkers!$A$2:$A$13,$A6,Checkers!$B$2:$B$13,$B6) -> 0 | J6: =SUMIFS(Checkers!$L$2:$L$13,Checkers!$A$2:$A$13,$A6,Checkers!$B$2:$B$13,$B6)&" of "&C6 -> 3 of 3 | K6: =AVERAGEIFS(Checkers!$M$2:$M$13,Checkers!$A$2:$A$13,$A6,Checkers!$B$2:$B$13,$B6) -> 86955
A7: Test 2: House Cab | B7: Old (A) | C7: =COUNTIFS(Checkers!$A$2:$A$13,$A7,Checkers!$B$2:$B$13,$B7) -> 3 | D7: =SUMIFS(Checkers!$F$2:$F$13,Checkers!$A$2:$A$13,$A7,Checkers!$B$2:$B$13,$B7) -> 28 | E7: =SUMIFS(Checkers!$E$2:$E$13,Checkers!$A$2:$A$13,$A7,Checkers!$B$2:$B$13,$B7) -> 30 | F7: =D7/E7 -> 0.93333333 | G7: =SUMIFS(Checkers!$I$2:$I$13,Checkers!$A$2:$A$13,$A7,Checkers!$B$2:$B$13,$B7)&" of "&C7 -> 1 of 3 | H7: =SUMIFS(Checkers!$J$2:$J$13,Checkers!$A$2:$A$13,$A7,Checkers!$B$2:$B$13,$B7) -> 0 | I7: =SUMIFS(Checkers!$K$2:$K$13,Checkers!$A$2:$A$13,$A7,Checkers!$B$2:$B$13,$B7) -> 1 | J7: =SUMIFS(Checkers!$L$2:$L$13,Checkers!$A$2:$A$13,$A7,Checkers!$B$2:$B$13,$B7)&" of "&C7 -> 0 of 3 | K7: =AVERAGEIFS(Checkers!$M$2:$M$13,Checkers!$A$2:$A$13,$A7,Checkers!$B$2:$B$13,$B7) -> 90424.667
A8: Test 2: House Cab | B8: New (B) | C8: =COUNTIFS(Checkers!$A$2:$A$13,$A8,Checkers!$B$2:$B$13,$B8) -> 3 | D8: =SUMIFS(Checkers!$F$2:$F$13,Checkers!$A$2:$A$13,$A8,Checkers!$B$2:$B$13,$B8) -> 30 | E8: =SUMIFS(Checkers!$E$2:$E$13,Checkers!$A$2:$A$13,$A8,Checkers!$B$2:$B$13,$B8) -> 30 | F8: =D8/E8 -> 1 | G8: =SUMIFS(Checkers!$I$2:$I$13,Checkers!$A$2:$A$13,$A8,Checkers!$B$2:$B$13,$B8)&" of "&C8 -> 3 of 3 | H8: =SUMIFS(Checkers!$J$2:$J$13,Checkers!$A$2:$A$13,$A8,Checkers!$B$2:$B$13,$B8) -> 0 | I8: =SUMIFS(Checkers!$K$2:$K$13,Checkers!$A$2:$A$13,$A8,Checkers!$B$2:$B$13,$B8) -> 0 | J8: =SUMIFS(Checkers!$L$2:$L$13,Checkers!$A$2:$A$13,$A8,Checkers!$B$2:$B$13,$B8)&" of "&C8 -> 3 of 3 | K8: =AVERAGEIFS(Checkers!$M$2:$M$13,Checkers!$A$2:$A$13,$A8,Checkers!$B$2:$B$13,$B8) -> 91952.667
A10: Findings
A11: • Test 1 (Sonnet, obvious errors): tie, 24/24 both arms. Ceiling effect.
A12: • Test 2 (Haiku, subtle errors): new rules 30/30 vs old 28/30. Both old misses = strawman 'case against' section.
A13: • Real gain = dissent check. Rest of error-first list mostly duplicated existing step 3.
A14: • New rules labeled strategy call 'judgment, not verified' 6 of 6; old 0 of 6.
A15: • Cost: ~1-2% more tokens per checker.
A16: • Limits: 12 runs, two memos, all-Claude checkers, author wrote errors and key. Directional, not proof.
A17: • Answer keys sealed (AES) before launch; SHA-256 prefixes matched on unseal: 3bff45b3ee1457e3, 946c4c2e4520f1f6.

Sheet Checkers
A1: Test | B1: Rules | C1: Checker | D1: Model | E1: Planted errors | F1: Caught | G1: Missed | H1: Catch rate | I1: Dissent flagged (1/0) | J1: Decoys wrongly flagged | K1: Nitpick false flags | L1: Judgment labeled (1/0) | M1: Tokens | N1: Verdict
A2: Test 1: Coravin | B2: Old (A) | C2: A1 | D2: Sonnet | E2: 8 | F2: 8 | G2: =E2-F2 -> 0 | H2: =F2/E2 -> 1 | I2: 1 | J2: 0 | K2: 0 | L2: 0 | M2: 86452 | N2: FAIL
A3: Test 1: Coravin | B3: Old (A) | C3: A2 | D3: Sonnet | E3: 8 | F3: 8 | G3: =E3-F3 -> 0 | H3: =F3/E3 -> 1 | I3: 1 | J3: 0 | K3: 0 | L3: 0 | M3: 86409 | N3: FAIL
A4: Test 1: Coravin | B4: Old (A) | C4: A3 | D4: Sonnet | E4: 8 | F4: 8 | G4: =E4-F4 -> 0 | H4: =F4/E4 -> 1 | I4: 1 | J4: 0 | K4: 0 | L4: 0 | M4: 86189 | N4: FAIL
A5: Test 1: Coravin | B5: New (B) | C5: B1 | D5: Sonnet | E5: 8 | F5: 8 | G5: =E5-F5 -> 0 | H5: =F5/E5 -> 1 | I5: 1 | J5: 0 | K5: 0 | L5: 1 | M5: 86981 | N5: FAIL
A6: Test 1: Coravin | B6: New (B) | C6: B2 | D6: Sonnet | E6: 8 | F6: 8 | G6: =E6-F6 -> 0 | H6: =F6/E6 -> 1 | I6: 1 | J6: 0 | K6: 0 | L6: 1 | M6: 86961 | N6: FAIL
A7: Test 1: Coravin | B7: New (B) | C7: B3 | D7: Sonnet | E7: 8 | F7: 8 | G7: =E7-F7 -> 0 | H7: =F7/E7 -> 1 | I7: 1 | J7: 0 | K7: 0 | L7: 1 | M7: 86923 | N7: FAIL
A8: Test 2: House Cab | B8: Old (A) | C8: A1 | D8: Haiku | E8: 10 | F8: 9 | G8: =E8-F8 -> 1 | H8: =F8/E8 -> 0.9 | I8: 0 | J8: 0 | K8: 1 | L8: 0 | M8: 91471 | N8: FAIL
A9: Test 2: House Cab | B9: Old (A) | C9: A2 | D9: Haiku | E9: 10 | F9: 9 | G9: =E9-F9 -> 1 | H9: =F9/E9 -> 0.9 | I9: 0 | J9: 0 | K9: 0 | L9: 0 | M9: 90022 | N9: FAIL
A10: Test 2: House Cab | B10: Old (A) | C10: A3 | D10: Haiku | E10: 10 | F10: 10 | G10: =E10-F10 -> 0 | H10: =F10/E10 -> 1 | I10: 1 | J10: 0 | K10: 0 | L10: 0 | M10: 89781 | N10: FAIL
A11: Test 2: House Cab | B11: New (B) | C11: B1 | D11: Haiku | E11: 10 | F11: 10 | G11: =E11-F11 -> 0 | H11: =F11/E11 -> 1 | I11: 1 | J11: 0 | K11: 0 | L11: 1 | M11: 91072 | N11: FAIL
A12: Test 2: House Cab | B12: New (B) | C12: B2 | D12: Haiku | E12: 10 | F12: 10 | G12: =E12-F12 -> 0 | H12: =F12/E12 -> 1 | I12: 1 | J12: 0 | K12: 0 | L12: 1 | M12: 91393 | N12: FAIL
A13: Test 2: House Cab | B13: New (B) | C13: B3 | D13: Haiku | E13: 10 | F13: 10 | G13: =E13-F13 -> 0 | H13: =F13/E13 -> 1 | I13: 1 | J13: 0 | K13: 0 | L13: 1 | M13: 93393 | N13: FAIL
A15: Source: subagent results, this session (2026-10-24). Blue = recorded values; black = formulas.

Sheet Planted Errors
A1: Test | B1: ID | C1: Planted error | D1: Type | E1: A1 | F1: A2 | G1: A3 | H1: B1 | I1: B2 | J1: B3 | K1: Old caught | L1: New caught
A2: Test 1: Coravin | B2: E1 | C2: '$2,200 total' (4 x $450 = $1,800) | D2: Arithmetic | E2: 1 | F2: 1 | G2: 1 | H2: 1 | I2: 1 | J2: 1 | K2: =SUM(E2:G2)&"/3" -> 3/3 | L2: =SUM(H2:J2)&"/3" -> 3/3
A3: Test 1: Coravin | B3: E2 | C3: 'Fits comfortably within capital budget' (only $1,500 left) | D3: Contradicts spec | E3: 1 | F3: 1 | G3: 1 | H3: 1 | I3: 1 | J3: 1 | K3: =SUM(E3:G3)&"/3" -> 3/3 | L3: =SUM(H3:J3)&"/3" -> 3/3
A4: Test 1: Coravin | B4: E3 | C4: 'Club X's results prove' sales will rise 15% | D4: Overstatement | E4: 1 | F4: 1 | G4: 1 | H4: 1 | I4: 1 | J4: 1 | K4: =SUM(E4:G4)&"/3" -> 3/3 | L4: =SUM(H4:J4)&"/3" -> 3/3
A5: Test 1: Coravin | B5: E4 | C5: Older members will pay more for premium | D5: Non-sequitur | E5: 1 | F5: 1 | G5: 1 | H5: 1 | I5: 1 | J5: 1 | K5: =SUM(E5:G5)&"/3" -> 3/3 | L5: =SUM(H5:J5)&"/3" -> 3/3
A6: Test 1: Coravin | B6: E5 | C6: 'Coravin always eliminates oxidation waste' | D6: Overstatement | E6: 1 | F6: 1 | G6: 1 | H6: 1 | I6: 1 | J6: 1 | K6: =SUM(E6:G6)&"/3" -> 3/3 | L6: =SUM(H6:J6)&"/3" -> 3/3
A7: Test 1: Coravin | B7: E6 | C7: 'From 10 to 16 wines' (12 to 18) | D7: Contradicts spec | E7: 1 | F7: 1 | G7: 1 | H7: 1 | I7: 1 | J7: 1 | K7: =SUM(E7:G7)&"/3" -> 3/3 | L7: =SUM(H7:J7)&"/3" -> 3/3
A8: Test 1: Coravin | B8: E7 | C8: Payback under 4 months ignores $300/mo argon | D8: Logic | E8: 1 | F8: 1 | G8: 1 | H8: 1 | I8: 1 | J8: 1 | K8: =SUM(E8:G8)&"/3" -> 3/3 | L8: =SUM(H8:J8)&"/3" -> 3/3
A9: Test 1: Coravin | B9: E8 | C9: Only argument against = staff training | D9: Strawman dissent | E9: 1 | F9: 1 | G9: 1 | H9: 1 | I9: 1 | J9: 1 | K9: =SUM(E9:G9)&"/3" -> 3/3 | L9: =SUM(H9:J9)&"/3" -> 3/3
A10: Test 2: House Cab | B10: E1 | C10: Net savings '$7,800' (actual $6,744) | D10: Arithmetic | E10: 1 | F10: 1 | G10: 1 | H10: 1 | I10: 1 | J10: 1 | K10: =SUM(E10:G10)&"/3" -> 3/3 | L10: =SUM(H10:J10)&"/3" -> 3/3
A11: Test 2: House Cab | B11: E2 | C11: Tasting 'clearly showed' preference (5 vs 4) | D11: Overstatement | E11: 1 | F11: 1 | G11: 1 | H11: 1 | I11: 1 | J11: 1 | K11: =SUM(E11:G11)&"/3" -> 3/3 | L11: =SUM(H11:J11)&"/3" -> 3/3
A12: Test 2: House Cab | B12: E3 | C12: Survey means members 'unlikely to notice' | D12: Non-sequitur | E12: 1 | F12: 1 | G12: 1 | H12: 1 | I12: 1 | J12: 1 | K12: =SUM(E12:G12)&"/3" -> 3/3 | L12: =SUM(H12:J12)&"/3" -> 3/3
A13: Test 2: House Cab | B13: E4 | C13: New supplier 'lowers our supply risk' | D13: Logic | E13: 1 | F13: 1 | G13: 1 | H13: 1 | I13: 1 | J13: 1 | K13: =SUM(E13:G13)&"/3" -> 3/3 | L13: =SUM(H13:J13)&"/3" -> 3/3
... A19: Test 2: House Cab | B19: E10 | C19: Case against = 'members may prefer what they know' | D19: Strawman dissent | E19: 0 | F19: 0 | G19: 1 | H19: 1 | I19: 1 | J19: 1 | K19: =SUM(E19:G19)&"/3" -> 1/3 | L19: =SUM(H19:J19)&"/3" -> 3/3
A21: 1 = flagged, 0 = missed. Red = missed.
